web_recruitment_sdk/__init__.py
web_recruitment_sdk/_base_client.py
web_recruitment_sdk/_client.py
web_recruitment_sdk/_compat.py
web_recruitment_sdk/_constants.py
web_recruitment_sdk/_exceptions.py
web_recruitment_sdk/_files.py
web_recruitment_sdk/_models.py
web_recruitment_sdk/_qs.py
web_recruitment_sdk/_resource.py
web_recruitment_sdk/_response.py
web_recruitment_sdk/_streaming.py
web_recruitment_sdk/_types.py
web_recruitment_sdk/_version.py
web_recruitment_sdk/py.typed
web_recruitment_sdk/_utils/__init__.py
web_recruitment_sdk/_utils/_compat.py
web_recruitment_sdk/_utils/_datetime_parse.py
web_recruitment_sdk/_utils/_logs.py
web_recruitment_sdk/_utils/_proxy.py
web_recruitment_sdk/_utils/_reflection.py
web_recruitment_sdk/_utils/_resources_proxy.py
web_recruitment_sdk/_utils/_streams.py
web_recruitment_sdk/_utils/_sync.py
web_recruitment_sdk/_utils/_transform.py
web_recruitment_sdk/_utils/_typing.py
web_recruitment_sdk/_utils/_utils.py
web_recruitment_sdk/lib/.keep
web_recruitment_sdk/resources/__init__.py
web_recruitment_sdk/resources/appointments.py
web_recruitment_sdk/resources/auth.py
web_recruitment_sdk/resources/criteria.py
web_recruitment_sdk/resources/custom_criteria.py
web_recruitment_sdk/resources/dashboards.py
web_recruitment_sdk/resources/export_jobs.py
web_recruitment_sdk/resources/health.py
web_recruitment_sdk/resources/matching_jobs.py
web_recruitment_sdk/resources/patients_by_external_id.py
web_recruitment_sdk/resources/sites.py
web_recruitment_sdk/resources/admin/__init__.py
web_recruitment_sdk/resources/admin/admin.py
web_recruitment_sdk/resources/admin/users.py
web_recruitment_sdk/resources/crio/__init__.py
web_recruitment_sdk/resources/crio/clients.py
web_recruitment_sdk/resources/crio/crio.py
web_recruitment_sdk/resources/custom_searches/__init__.py
web_recruitment_sdk/resources/custom_searches/criteria.py
web_recruitment_sdk/resources/custom_searches/custom_searches.py
web_recruitment_sdk/resources/custom_searches/user_criteria.py
web_recruitment_sdk-0.1.0a23.dist-info/METADATA
web_recruitment_sdk-0.1.0a23.dist-info/WHEEL
web_recruitment_sdk-0.1.0a23.dist-info/licenses/LICENSE
web_recruitment_sdk-0.1.0a23.dist-info/RECORD
